Y2T/Collection.py
Y2T/Log.py
Y2T/Nfo.py
Y2T/Playlist.py
Y2T/Presentation.py
Y2T/Torrent.py
Y2T/Utils.py
Y2T/Video.py
Y2T/Y2T.py
Y2T/__init__.py
Y2T-1.5.dist-info/LICENSE
Y2T-1.5.dist-info/METADATA
Y2T-1.5.dist-info/WHEEL
Y2T-1.5.dist-info/top_level.txt
Y2T-1.5.dist-info/RECORD
