Metadata-Version: 2.1
Name: Y2T
Version: 1.5
Summary: Youtube to Torrent
Home-page: https://github.com/Esisar-Pro-G/Y2T
Author: Esisar Pro-G
Author-email: esisar.pro.g@gmail.com
License: UNKNOWN
Platform: Linux
Requires-Dist: youtube-dl
Requires-Dist: mutagen
